astjson/__init__.py
astjson/astjson.py
astjson-0.0.1.dist-info/METADATA
astjson-0.0.1.dist-info/WHEEL
astjson-0.0.1.dist-info/licenses/LICENSE.txt
astjson-0.0.1.dist-info/RECORD
