Metadata-Version: 2.3
Name: astjson
Version: 0.0.1
Summary: AST to JSON converter
Project-URL: Homepage, https://github.com/jslambda/astjson/
Project-URL: Issues, https://github.com/jslambda/astjson/issues
Author-email: Hamid Alavi Toussi <hamidjslambda@gmail.com>
License-File: LICENSE.txt
Classifier: License :: OSI Approved :: MIT License
Classifier: Operating System :: OS Independent
Classifier: Programming Language :: Python :: 3
Requires-Python: >=3.8
